checker_SaGaF/__init__.py
checker_SaGaF/checker_SaGaF.py
checker_SaGaF-0.1.dist-info/METADATA
checker_SaGaF-0.1.dist-info/WHEEL
checker_SaGaF-0.1.dist-info/top_level.txt
checker_SaGaF-0.1.dist-info/RECORD
