Metadata-Version: 2.1
Name: checker-SaGaF
Version: 0.1
Summary: Checker vaild emails for tiktok or instagram .
Author: @CCIIUU
Author-email: dxa00776@gmail.com
Classifier: Programming Language :: Python :: 3
Classifier: Operating System :: OS Independent
Classifier: License :: OSI Approved :: MIT License
